pyloa/__init__.py
pyloa/_eval.py
pyloa/_gen.py
pyloa/_main.py
pyloa/_train.py
pyloa/_version.py
pyloa/agent/__init__.py
pyloa/agent/agent.py
pyloa/agent/pagingagent.py
pyloa/agent/qagent.py
pyloa/agent/qlstm.py
pyloa/agent/qlstmvertex.py
pyloa/agent/qmlp.py
pyloa/agent/qmlpvertex.py
pyloa/agent/qtable.py
pyloa/agent/rlagent.py
pyloa/agent/vertexagent.py
pyloa/environment/__init__.py
pyloa/environment/defaultenv.py
pyloa/environment/environment.py
pyloa/environment/normalizedenv.py
pyloa/environment/permutatedenv.py
pyloa/environment/vertexenv.py
pyloa/instance/__init__.py
pyloa/instance/graphgenerator.py
pyloa/instance/instancegenerator.py
pyloa/instance/markovseqgen.py
pyloa/instance/randomseqgen.py
pyloa/instance/seqgen.py
pyloa/utils/__init__.py
pyloa/utils/exception.py
pyloa/utils/format.py
pyloa/utils/graph.py
pyloa/utils/load.py
pyloa/utils/math.py
pyloa/utils/memory.py
pyloa/utils/sumtree.py
pyloa/utils/tensorboard.py
pyloa-1.0.3.dist-info/LICENSE
pyloa-1.0.3.dist-info/METADATA
pyloa-1.0.3.dist-info/WHEEL
pyloa-1.0.3.dist-info/entry_points.txt
pyloa-1.0.3.dist-info/top_level.txt
pyloa-1.0.3.dist-info/RECORD
