Metadata-Version: 2.1
Name: pyloa
Version: 1.0.3
Summary: PyLoa: Learning on-line Algorithms with Python
Home-page: https://github.com/pyloa/PyLoa
Author: PyLoa Developers
Author-email: pyloadevelopers@gmail.com
Maintainer: PyLoa Developers
Maintainer-email: pyloadevelopers@gmail.com
License: MIT
Project-URL: Documentation, https://github.com/pyloa/PyLoa/tree/master/pyloa
Project-URL: Bug Tracker, https://github.com/pyloa/PyLoa/issues
Project-URL: Source Code, https://github.com/pyloa/PyLoa/tree/master/pyloa
Keywords: on-line algorithms,paging,vertex coloring,machine learning
Platform: any
Classifier: Development Status :: 3 - Alpha
Classifier: Intended Audience :: Science/Research
Classifier: Intended Audience :: Education
Classifier: Intended Audience :: Developers
Classifier: License :: OSI Approved :: MIT License
Classifier: Programming Language :: Python :: 3.5
Classifier: Programming Language :: Python :: 3.6
Classifier: Programming Language :: Python :: 3.7
Classifier: Topic :: Scientific/Engineering
Classifier: Operating System :: Microsoft :: Windows
Classifier: Operating System :: POSIX
Classifier: Operating System :: Unix
Classifier: Operating System :: MacOS
Provides: pyloa
Requires-Python: >=3.5
Requires-Dist: matplotlib (==3.0.3)
Requires-Dist: scipy (==1.2.1)
Requires-Dist: tensorflow (==1.13.1)
Requires-Dist: tqdm (==4.31.1)
Requires-Dist: numpy (==1.16.2)
